worldmodel_hub/__init__.py
worldmodel_hub-0.0.1.dist-info/METADATA
worldmodel_hub-0.0.1.dist-info/WHEEL
worldmodel_hub-0.0.1.dist-info/licenses/LICENSE
worldmodel_hub-0.0.1.dist-info/RECORD
