Metadata-Version: 2.4
Name: worldmodel-hub
Version: 0.0.1
Summary: A standardized API for interacting with world models.
Project-URL: Homepage, https://competesai.com
Project-URL: Documentation, https://wm.competesai.com
Author-email: ArenaX Labs <research@competesai.com>
License: MIT
License-File: LICENSE
Classifier: Programming Language :: Python :: 3
Classifier: Programming Language :: Python :: 3.10
Classifier: Programming Language :: Python :: 3.11
Classifier: Programming Language :: Python :: 3.12
Requires-Python: >=3.10
Requires-Dist: gymnasium<1.2.0,>=1.0.0
Requires-Dist: mujoco<4,>=3.1.6
Requires-Dist: numpy<3.0,>=2.0.0
Requires-Dist: opencv-contrib-python<5.0,>=4.8.0.74
Requires-Dist: pydantic<3.0,>=2
Requires-Dist: pyquaternion<1.0,>=0.9.9
Requires-Dist: pyyaml<7.0,>=6
Requires-Dist: scipy<2.0,>=1.10.1
